_cmtj.cp312-win_amd64.pyd
cmtj/__init__.py
cmtj/__init__.pyi
cmtj/_version.py
cmtj/py.typed
cmtj/core/__init__.py
cmtj/core/__init__.pyi
cmtj/llgb/__init__.py
cmtj/llgb/__init__.pyi
cmtj/models/__init__.py
cmtj/models/analytical_utils.py
cmtj/models/domain_dynamics.py
cmtj/models/drivers.py
cmtj/models/ensemble.py
cmtj/models/general_sb.py
cmtj/models/noise.py
cmtj/models/oersted.py
cmtj/noise/__init__.py
cmtj/noise/__init__.pyi
cmtj/reservoir/__init__.py
cmtj/reservoir/__init__.pyi
cmtj/stack/__init__.py
cmtj/stack/__init__.pyi
cmtj/utils/__init__.py
cmtj/utils/constants.py
cmtj/utils/demag.py
cmtj/utils/energy.py
cmtj/utils/filters.py
cmtj/utils/general.py
cmtj/utils/linear.py
cmtj/utils/optimization.py
cmtj/utils/parallel.py
cmtj/utils/plotting.py
cmtj/utils/procedures.py
cmtj/utils/resistance.py
cmtj/utils/solvers.py
cmtj-1.11.0.dist-info/licenses/LICENSE
cmtj-1.11.0.dist-info/METADATA
cmtj-1.11.0.dist-info/WHEEL
cmtj-1.11.0.dist-info/top_level.txt
cmtj-1.11.0.dist-info/RECORD
