Metadata-Version: 2.4
Name: cmtj
Version: 1.11.0
Summary: CMTJ - C Magnetic Tunnel Junctions.
Author-email: Jakub <mojsieju@agh.edu.pl>
License: GPL-2.0-only
Project-URL: Homepage, https://github.com/LemurPwned/cmtj
Project-URL: Documentation, https://lemurpwned.github.io/cmtj
Project-URL: Repository, https://github.com/LemurPwned/cmtj
Project-URL: Issues, https://github.com/LemurPwned/cmtj/issues
Keywords: magnetics,physics,simulation,spintronics
Classifier: Programming Language :: Python :: 3
Classifier: Programming Language :: Python :: 3.9
Classifier: Programming Language :: Python :: 3.10
Classifier: Programming Language :: Python :: 3.11
Classifier: Programming Language :: Python :: 3.12
Classifier: Programming Language :: C++
Classifier: Operating System :: OS Independent
Classifier: Topic :: Scientific/Engineering
Classifier: Topic :: Scientific/Engineering :: Physics
Classifier: Typing :: Stubs Only
Classifier: Typing :: Typed
Requires-Python: >=3.9
License-File: LICENSE
Requires-Dist: numpy>=1.25.0
Requires-Dist: numba>=0.60.0
Requires-Dist: sympy>=1.14.0
Requires-Dist: scipy>=1.13.1
Requires-Dist: tqdm>=4.63.3
Provides-Extra: utils
Requires-Dist: matplotlib; extra == "utils"
Requires-Dist: pandas; extra == "utils"
Requires-Dist: multiprocess; extra == "utils"
Provides-Extra: test
Requires-Dist: pytest; extra == "test"
Provides-Extra: dev
Requires-Dist: pytest; extra == "dev"
Requires-Dist: pre-commit; extra == "dev"
Requires-Dist: ruff; extra == "dev"
Requires-Dist: mypy; extra == "dev"
Requires-Dist: pybind11-stubgen; extra == "dev"
Provides-Extra: docs
Requires-Dist: mkdocs; extra == "docs"
Requires-Dist: mkdocs-material; extra == "docs"
Requires-Dist: mkdocs-gen-files; extra == "docs"
Requires-Dist: mkdocs-literate-nav; extra == "docs"
Requires-Dist: mkdocs-section-index; extra == "docs"
Requires-Dist: mkdocstrings[python]; extra == "docs"
Dynamic: license-file
